{
	"-1":{
		"name": "famine!",
		"text":	"Le manque de nourriture commence à se faire ressentir dans les secteurs inférieurs, capitaine. Nos passagers meurent de faim !",

		"effects":[{
				"gauge" : "population",
				"apply" : "-5"
		}
		],

		"resolution" : [{
				"ressource" : "food",
				"apply" : "-6"
		}
		],

		"consequences" : [{
			"turn" : "1",
			"name" : "riots"

		}
		],

		"onResolve" : {
			"text": "La distribution de nourriture a commencé sous les hourras. La foule scandait votre nom, Capitaine !\nMais vous connaissez les habitants des bas-fonds... Certains ont tenter de gruger la file d'attente\net la situation a dégénéré en pugilat. L'avantage, c'est que vu le nombre de morts,\nvous n'avez plus à vous soucier de la famine, désormais !",
			"gauge": [{
				"name" : "population",
				"apply" : "-20"
			}]
		},

	}


}
